hstest/__init__.py
hstest/check_result.py
hstest/common/__init__.py
hstest/common/file_utils.py
hstest/common/os_utils.py
hstest/common/process_utils.py
hstest/common/reflection_utils.py
hstest/common/utils.py
hstest/dynamic/__init__.py
hstest/dynamic/dynamic_test.py
hstest/dynamic/input/__init__.py
hstest/dynamic/input/dynamic_input_func.py
hstest/dynamic/input/dynamic_input_handler.py
hstest/dynamic/input/dynamic_testing.py
hstest/dynamic/input/input_handler.py
hstest/dynamic/input/input_mock.py
hstest/dynamic/output/__init__.py
hstest/dynamic/output/colored_output.py
hstest/dynamic/output/infinite_loop_detector.py
hstest/dynamic/output/output_handler.py
hstest/dynamic/output/output_mock.py
hstest/dynamic/security/__init__.py
hstest/dynamic/security/exit_exception.py
hstest/dynamic/security/exit_handler.py
hstest/dynamic/security/thread_group.py
hstest/dynamic/security/thread_handler.py
hstest/dynamic/system_handler.py
hstest/exception/__init__.py
hstest/exception/failure_handler.py
hstest/exception/outcomes.py
hstest/exception/testing.py
hstest/exceptions.py
hstest/outcomes/__init__.py
hstest/outcomes/compilation_error_outcome.py
hstest/outcomes/error_outcome.py
hstest/outcomes/exception_outcome.py
hstest/outcomes/outcome.py
hstest/outcomes/unexpected_error_outcome.py
hstest/outcomes/wrong_answer_outcome.py
hstest/stage/__init__.py
hstest/stage/django_test.py
hstest/stage/flask_test.py
hstest/stage/plotting_test.py
hstest/stage/sql_test.py
hstest/stage/stage_test.py
hstest/stage_test.py
hstest/test_case/__init__.py
hstest/test_case/attach/__init__.py
hstest/test_case/attach/django_settings.py
hstest/test_case/attach/flask_settings.py
hstest/test_case/check_result.py
hstest/test_case/test_case.py
hstest/testing/__init__.py
hstest/testing/execution/__init__.py
hstest/testing/execution/filtering/__init__.py
hstest/testing/execution/filtering/file_filter.py
hstest/testing/execution/filtering/main_filter.py
hstest/testing/execution/main_module_executor.py
hs_test_python-11.0.30.dist-info/METADATA
hs_test_python-11.0.30.dist-info/WHEEL
hs_test_python-11.0.30.dist-info/RECORD
