Metadata-Version: 2.3
Name: hs-test-python
Version: 11.0.30
Summary: A framework that simplifies testing educational projects for Hyperskill with features like black box testing, multiple test types support, and learner-friendly feedback generation.
Author: Hyperskill Team
Requires-Python: >=3.10,<4.0
Classifier: Programming Language :: Python :: 3
Classifier: Programming Language :: Python :: 3.10
Classifier: Programming Language :: Python :: 3.11
Classifier: Programming Language :: Python :: 3.12
Classifier: Programming Language :: Python :: 3.13
Requires-Dist: matplotlib (>=3.9.2,<4.0.0)
Requires-Dist: pandas (==2.2.3)
Requires-Dist: psutil (==7.0.0)
Requires-Dist: scipy (==1.15.3)
Requires-Dist: seaborn (==0.13.2)
